README.md
setup.py
vkbotfather/__init__.py
vkbotfather.egg-info/PKG-INFO
vkbotfather.egg-info/SOURCES.txt
vkbotfather.egg-info/dependency_links.txt
vkbotfather.egg-info/requires.txt
vkbotfather.egg-info/top_level.txt
vkbotfather/fatherbot/__init__.py
vkbotfather/fatherbot/bot.py
vkbotfather/fatherbot/models/__init__.py
vkbotfather/fatherbot/models/model.py
vkbotfather/fatherbot/models/settings.py
vkbotfather/fatherbot/models/vkapi.py
vkbotfather/plugins/__init__.py
vkbotfather/plugins/chat/__init__.py
vkbotfather/plugins/chat/about.py
vkbotfather/plugins/chat/allmemberchat.py
vkbotfather/plugins/chat/getinfo.py
vkbotfather/plugins/chat/kickuser.py
vkbotfather/plugins/chat/talk.py
vkbotfather/plugins/chat/whatchoose.py
vkbotfather/plugins/chat/whatrandom.py
vkbotfather/plugins/groups/__init__.py
vkbotfather/plugins/groups/allbanned.py
vkbotfather/plugins/groups/allmember.py
vkbotfather/plugins/groups/ismember.py
vkbotfather/utils/__init__.py
vkbotfather/utils/config_tool.py