Metadata-Version: 1.0
Name: vkbotfather
Version: 0.3.1
Summary: Father for creating VK Bots
Home-page: https://github.com/wultes/vkbotfather
Author: Wultes (Kirill)
Author-email: wultesu@gmail.com
License: MIT
Platform: UNKNOWN
